keras_loves_torchtext-0.0.1.1.dist-info/METADATA
keras_loves_torchtext-0.0.1.1.dist-info/RECORD
keras_loves_torchtext-0.0.1.1.dist-info/WHEEL
keras_loves_torchtext-0.0.1.1.dist-info/top_level.txt
keras_loves_torchtext-0.0.1.1.dist-info/zip-safe
kltt/__init__.py
