Metadata-Version: 2.1
Name: keras-loves-torchtext
Version: 0.0.1.1
Summary: Make torchtext work with Keras
Home-page: https://github.com/kklemon/keras-loves-torchtext
Author: Kristian Klemon
Author-email: kristian.klemon@gmail.com
License: BSD
Platform: UNKNOWN
